{
  "uniqueId": "stations_ishikawa",
  "name": "Ishikawa Stations Reading Quiz",
  "article": "a",
  "instructions": "Type the reading of the below station name in Hiragana!",
  "questionCreationStrategy": "IMAGE",
  "dictionaryLinkStrategy": "PROVIDED_ON_CARD",
  "answerTimeLimitStrategy": "JAPANESE_SETTINGS",
  "cardPreprocessingStrategy": "NONE",
  "discordFinalAnswerListElementStrategy": "QUESTION_AND_ANSWER_LINK_QUESTION",
  "scoreAnswerStrategy": "ONE_ANSWER_ONE_POINT",
  "additionalAnswerWaitStrategy": "JAPANESE_SETTINGS",
  "discordIntermediateAnswerListElementStrategy": "CORRECT_ANSWERS",
  "answerCompareStrategy": "CONVERT_KANA",
  "commentFieldName": "Line(s)",
  "description": "[Ishikawa station names](https://mb.jorudan.co.jp/os/eki/menu_kmq/)",
  "cards": [
    {
      "question": "穴水",
      "answer": [
        "あなみず"
      ],
      "meaning": "のと鉄道",
      "dictionaryLinkUri": "https://mb.jorudan.co.jp/os/eki/anamizu/"
    },
    {
      "question": "粟ヶ崎",
      "answer": [
        "あわがさき"
      ],
      "meaning": "北陸鉄道浅野川線",
      "dictionaryLinkUri": "https://mb.jorudan.co.jp/os/eki/awagasaki/"
    },
    {
      "question": "粟津",
      "answer": [
        "あわづ"
      ],
      "meaning": "北陸本線",
      "dictionaryLinkUri": "https://mb.jorudan.co.jp/os/eki/awazu_ishikawa/"
    },
    {
      "question": "磯部",
      "answer": [
        "いそべ"
      ],
      "meaning": "北陸鉄道浅野川線",
      "dictionaryLinkUri": "https://mb.jorudan.co.jp/os/eki/isobe_ishikawa/"
    },
    {
      "question": "井口",
      "answer": [
        "いのくち"
      ],
      "meaning": "北陸鉄道石川線",
      "dictionaryLinkUri": "https://mb.jorudan.co.jp/os/eki/inokuchi_ishikawa/"
    },
    {
      "question": "動橋",
      "answer": [
        "いぶりはし"
      ],
      "meaning": "北陸本線",
      "dictionaryLinkUri": "https://mb.jorudan.co.jp/os/eki/iburihashi/"
    },
    {
      "question": "内灘",
      "answer": [
        "うちなだ"
      ],
      "meaning": "北陸鉄道浅野川線",
      "dictionaryLinkUri": "https://mb.jorudan.co.jp/os/eki/uchinada/"
    },
    {
      "question": "宇野気",
      "answer": [
        "うのけ"
      ],
      "meaning": "七尾線",
      "dictionaryLinkUri": "https://mb.jorudan.co.jp/os/eki/unoke/"
    },
    {
      "question": "大河端",
      "answer": [
        "おこばた"
      ],
      "meaning": "北陸鉄道浅野川線",
      "dictionaryLinkUri": "https://mb.jorudan.co.jp/os/eki/okobata/"
    },
    {
      "question": "押野",
      "answer": [
        "おしの"
      ],
      "meaning": "北陸鉄道石川線",
      "dictionaryLinkUri": "https://mb.jorudan.co.jp/os/eki/oshino/"
    },
    {
      "question": "乙丸",
      "answer": [
        "おとまる"
      ],
      "meaning": "北陸鉄道石川線",
      "dictionaryLinkUri": "https://mb.jorudan.co.jp/os/eki/otomaru/"
    },
    {
      "question": "小柳",
      "answer": [
        "おやなぎ"
      ],
      "meaning": "北陸鉄道石川線",
      "dictionaryLinkUri": "https://mb.jorudan.co.jp/os/eki/oyanagi_ishikawa/"
    },
    {
      "question": "加賀温泉",
      "answer": [
        "かがおんせん"
      ],
      "meaning": "北陸本線",
      "dictionaryLinkUri": "https://mb.jorudan.co.jp/os/eki/kagaonsen/"
    },
    {
      "question": "加賀笠間",
      "answer": [
        "かがかさま"
      ],
      "meaning": "北陸本線",
      "dictionaryLinkUri": "https://mb.jorudan.co.jp/os/eki/kaga-kasama/"
    },
    {
      "question": "蚊爪",
      "answer": [
        "かがつめ"
      ],
      "meaning": "北陸鉄道浅野川線",
      "dictionaryLinkUri": "https://mb.jorudan.co.jp/os/eki/kagatsume/"
    },
    {
      "question": "笠師保",
      "answer": [
        "かさしほ"
      ],
      "meaning": "のと鉄道",
      "dictionaryLinkUri": "https://mb.jorudan.co.jp/os/eki/kasashiho/"
    },
    {
      "question": "金沢",
      "answer": [
        "かなざわ"
      ],
      "meaning": "北陸本線、北陸新幹線、ＩＲいしかわ鉄道",
      "dictionaryLinkUri": "https://mb.jorudan.co.jp/os/eki/kanazawa/"
    },
    {
      "question": "金丸",
      "answer": [
        "かねまる"
      ],
      "meaning": "七尾線",
      "dictionaryLinkUri": "https://mb.jorudan.co.jp/os/eki/kanemaru/"
    },
    {
      "question": "上諸江",
      "answer": [
        "かみもろえ"
      ],
      "meaning": "北陸鉄道浅野川線",
      "dictionaryLinkUri": "https://mb.jorudan.co.jp/os/eki/kamimoroe/"
    },
    {
      "question": "北間",
      "answer": [
        "きたま"
      ],
      "meaning": "北陸鉄道浅野川線",
      "dictionaryLinkUri": "https://mb.jorudan.co.jp/os/eki/kitama/"
    },
    {
      "question": "倶利伽羅",
      "answer": [
        "くりから"
      ],
      "meaning": "ＩＲいしかわ鉄道など",
      "dictionaryLinkUri": "https://mb.jorudan.co.jp/os/eki/kurikara/"
    },
    {
      "question": "小舞子",
      "answer": [
        "こまいこ"
      ],
      "meaning": "北陸本線",
      "dictionaryLinkUri": "https://mb.jorudan.co.jp/os/eki/komaiko/"
    },
    {
      "question": "小松",
      "answer": [
        "こまつ"
      ],
      "meaning": "北陸本線",
      "dictionaryLinkUri": "https://mb.jorudan.co.jp/os/eki/komatsu/"
    },
    {
      "question": "敷浪",
      "answer": [
        "しきなみ"
      ],
      "meaning": "七尾線",
      "dictionaryLinkUri": "https://mb.jorudan.co.jp/os/eki/shikinami/"
    },
    {
      "question": "四十万",
      "answer": [
        "しじま"
      ],
      "meaning": "北陸鉄道石川線",
      "dictionaryLinkUri": "https://mb.jorudan.co.jp/os/eki/shijima/"
    },
    {
      "question": "新西金沢",
      "answer": [
        "しんにしかなざわ"
      ],
      "meaning": "北陸鉄道石川線",
      "dictionaryLinkUri": "https://mb.jorudan.co.jp/os/eki/shin-nishikanazawa/"
    },
    {
      "question": "曽谷",
      "answer": [
        "そだに"
      ],
      "meaning": "北陸鉄道石川線",
      "dictionaryLinkUri": "https://mb.jorudan.co.jp/os/eki/sodani/"
    },
    {
      "question": "高松",
      "answer": [
        "たかまつ"
      ],
      "meaning": "七尾線",
      "dictionaryLinkUri": "https://mb.jorudan.co.jp/os/eki/takamatsu_ishikawa/"
    },
    {
      "question": "田鶴浜",
      "answer": [
        "たつるはま"
      ],
      "meaning": "のと鉄道",
      "dictionaryLinkUri": "https://mb.jorudan.co.jp/os/eki/tatsuruhama/"
    },
    {
      "question": "大聖寺",
      "answer": [
        "だいしょうじ"
      ],
      "meaning": "北陸本線",
      "dictionaryLinkUri": "https://mb.jorudan.co.jp/os/eki/daishoji/"
    },
    {
      "question": "千路",
      "answer": [
        "ちじ"
      ],
      "meaning": "七尾線",
      "dictionaryLinkUri": "https://mb.jorudan.co.jp/os/eki/chiji/"
    },
    {
      "question": "津幡",
      "answer": [
        "つばた"
      ],
      "meaning": "七尾線、ＩＲいしかわ鉄道",
      "dictionaryLinkUri": "https://mb.jorudan.co.jp/os/eki/tsubata/"
    },
    {
      "question": "鶴来",
      "answer": [
        "つるぎ"
      ],
      "meaning": "北陸鉄道石川線",
      "dictionaryLinkUri": "https://mb.jorudan.co.jp/os/eki/tsurugi/"
    },
    {
      "question": "徳田",
      "answer": [
        "とくだ"
      ],
      "meaning": "七尾線",
      "dictionaryLinkUri": "https://mb.jorudan.co.jp/os/eki/tokuda_ishikawa/"
    },
    {
      "question": "道法寺",
      "answer": [
        "どうほうじ"
      ],
      "meaning": "北陸鉄道石川線",
      "dictionaryLinkUri": "https://mb.jorudan.co.jp/os/eki/dohoji/"
    },
    {
      "question": "中津幡",
      "answer": [
        "なかつばた"
      ],
      "meaning": "七尾線",
      "dictionaryLinkUri": "https://mb.jorudan.co.jp/os/eki/naka-tsubata/"
    },
    {
      "question": "七尾",
      "answer": [
        "ななお"
      ],
      "meaning": "七尾線、のと鉄道",
      "dictionaryLinkUri": "https://mb.jorudan.co.jp/os/eki/nanao/"
    },
    {
      "question": "七ッ屋",
      "answer": [
        "ななつや"
      ],
      "meaning": "北陸鉄道浅野川線",
      "dictionaryLinkUri": "https://mb.jorudan.co.jp/os/eki/nanatsuya/"
    },
    {
      "question": "西泉",
      "answer": [
        "にしいずみ"
      ],
      "meaning": "北陸鉄道石川線",
      "dictionaryLinkUri": "https://mb.jorudan.co.jp/os/eki/nishiizumi_ishikawa/"
    },
    {
      "question": "西金沢",
      "answer": [
        "にしかなざわ"
      ],
      "meaning": "北陸本線",
      "dictionaryLinkUri": "https://mb.jorudan.co.jp/os/eki/nishi-kanazawa/"
    },
    {
      "question": "西岸",
      "answer": [
        "にしぎし"
      ],
      "meaning": "のと鉄道",
      "dictionaryLinkUri": "https://mb.jorudan.co.jp/os/eki/nishigishi/"
    },
    {
      "question": "額住宅前",
      "answer": [
        "ぬかじゅうたくまえ"
      ],
      "meaning": "北陸鉄道石川線",
      "dictionaryLinkUri": "https://mb.jorudan.co.jp/os/eki/nukajutaku-mae/"
    },
    {
      "question": "能瀬",
      "answer": [
        "のせ"
      ],
      "meaning": "七尾線",
      "dictionaryLinkUri": "https://mb.jorudan.co.jp/os/eki/nose/"
    },
    {
      "question": "能登鹿島",
      "answer": [
        "のとかしま"
      ],
      "meaning": "のと鉄道",
      "dictionaryLinkUri": "https://mb.jorudan.co.jp/os/eki/noto-kashima/"
    },
    {
      "question": "能登中島",
      "answer": [
        "のとなかじま"
      ],
      "meaning": "のと鉄道",
      "dictionaryLinkUri": "https://mb.jorudan.co.jp/os/eki/noto-nakajima/"
    },
    {
      "question": "能登二宮",
      "answer": [
        "のとにのみや"
      ],
      "meaning": "七尾線",
      "dictionaryLinkUri": "https://mb.jorudan.co.jp/os/eki/noto-ninomiya/"
    },
    {
      "question": "能登部",
      "answer": [
        "のとべ"
      ],
      "meaning": "七尾線",
      "dictionaryLinkUri": "https://mb.jorudan.co.jp/os/eki/notobe/"
    },
    {
      "question": "野々市",
      "answer": [
        "ののいち"
      ],
      "meaning": "北陸鉄道石川線",
      "dictionaryLinkUri": "https://mb.jorudan.co.jp/os/eki/nonoichi_hokuriku/"
    },
    {
      "question": "野々市工大前",
      "answer": [
        "ののいちこうだいまえ"
      ],
      "meaning": "北陸鉄道石川線",
      "dictionaryLinkUri": "https://mb.jorudan.co.jp/os/eki/nonoichikodai-mae/"
    },
    {
      "question": "野町",
      "answer": [
        "のまち"
      ],
      "meaning": "北陸鉄道石川線",
      "dictionaryLinkUri": "https://mb.jorudan.co.jp/os/eki/nomachi_ishikawa/"
    },
    {
      "question": "能美根上",
      "answer": [
        "のみねあがり"
      ],
      "meaning": "北陸本線",
      "dictionaryLinkUri": "https://mb.jorudan.co.jp/os/eki/nomineagari/"
    },
    {
      "question": "羽咋",
      "answer": [
        "はくい"
      ],
      "meaning": "七尾線",
      "dictionaryLinkUri": "https://mb.jorudan.co.jp/os/eki/hakui/"
    },
    {
      "question": "東金沢",
      "answer": [
        "ひがしかなざわ"
      ],
      "meaning": "ＩＲいしかわ鉄道",
      "dictionaryLinkUri": "https://mb.jorudan.co.jp/os/eki/higashi-kanazawa/"
    },
    {
      "question": "日御子",
      "answer": [
        "ひのみこ"
      ],
      "meaning": "北陸鉄道石川線",
      "dictionaryLinkUri": "https://mb.jorudan.co.jp/os/eki/hinomiko/"
    },
    {
      "question": "陽羽里",
      "answer": [
        "ひばり"
      ],
      "meaning": "北陸鉄道石川線",
      "dictionaryLinkUri": "https://mb.jorudan.co.jp/os/eki/hibari/"
    },
    {
      "question": "宝達",
      "answer": [
        "ほうだつ"
      ],
      "meaning": "七尾線",
      "dictionaryLinkUri": "https://mb.jorudan.co.jp/os/eki/hodatsu/"
    },
    {
      "question": "北鉄金沢",
      "answer": [
        "ほくてつかなざわ"
      ],
      "meaning": "北陸鉄道浅野川線",
      "dictionaryLinkUri": "https://mb.jorudan.co.jp/os/eki/hokutetsu-kanazawa/"
    },
    {
      "question": "本津幡",
      "answer": [
        "ほんつばた"
      ],
      "meaning": "七尾線",
      "dictionaryLinkUri": "https://mb.jorudan.co.jp/os/eki/hon-tsubata/"
    },
    {
      "question": "馬替",
      "answer": [
        "まがえ"
      ],
      "meaning": "北陸鉄道石川線",
      "dictionaryLinkUri": "https://mb.jorudan.co.jp/os/eki/magae/"
    },
    {
      "question": "松任",
      "answer": [
        "まっとう"
      ],
      "meaning": "北陸本線",
      "dictionaryLinkUri": "https://mb.jorudan.co.jp/os/eki/matto/"
    },
    {
      "question": "美川",
      "answer": [
        "みかわ"
      ],
      "meaning": "北陸本線",
      "dictionaryLinkUri": "https://mb.jorudan.co.jp/os/eki/mikawa_ishikawa/"
    },
    {
      "question": "三口",
      "answer": [
        "みつくち"
      ],
      "meaning": "北陸鉄道浅野川線",
      "dictionaryLinkUri": "https://mb.jorudan.co.jp/os/eki/mitsukuchi/"
    },
    {
      "question": "三ッ屋",
      "answer": [
        "みつや"
      ],
      "meaning": "北陸鉄道浅野川線",
      "dictionaryLinkUri": "https://mb.jorudan.co.jp/os/eki/mitsuya/"
    },
    {
      "question": "南羽咋",
      "answer": [
        "みなみはくい"
      ],
      "meaning": "七尾線",
      "dictionaryLinkUri": "https://mb.jorudan.co.jp/os/eki/minami-hakui/"
    },
    {
      "question": "明峰",
      "answer": [
        "めいほう"
      ],
      "meaning": "北陸本線",
      "dictionaryLinkUri": "https://mb.jorudan.co.jp/os/eki/meiho/"
    },
    {
      "question": "免田",
      "answer": [
        "めんでん"
      ],
      "meaning": "七尾線",
      "dictionaryLinkUri": "https://mb.jorudan.co.jp/os/eki/menden_ishikawa/"
    },
    {
      "question": "森本",
      "answer": [
        "もりもと"
      ],
      "meaning": "ＩＲいしかわ鉄道",
      "dictionaryLinkUri": "https://mb.jorudan.co.jp/os/eki/morimoto/"
    },
    {
      "question": "横山",
      "answer": [
        "よこやま"
      ],
      "meaning": "七尾線",
      "dictionaryLinkUri": "https://mb.jorudan.co.jp/os/eki/yokoyama_ishikawa/"
    },
    {
      "question": "良川",
      "answer": [
        "よしかわ"
      ],
      "meaning": "七尾線",
      "dictionaryLinkUri": "https://mb.jorudan.co.jp/os/eki/yoshikawa_ishikawa/"
    },
    {
      "question": "和倉温泉",
      "answer": [
        "わくらおんせん"
      ],
      "meaning": "七尾線、のと鉄道",
      "dictionaryLinkUri": "https://mb.jorudan.co.jp/os/eki/wakuraonsen/"
    },
    {
      "question": "割出",
      "answer": [
        "わりだし"
      ],
      "meaning": "北陸鉄道浅野川線",
      "dictionaryLinkUri": "https://mb.jorudan.co.jp/os/eki/waridashi/"
    }
  ]
}