{
  "uniqueId": "stations_kagoshima",
  "name": "Kagoshima Stations Reading Quiz",
  "article": "a",
  "instructions": "Type the reading of the below station name in Hiragana!",
  "questionCreationStrategy": "IMAGE",
  "dictionaryLinkStrategy": "PROVIDED_ON_CARD",
  "answerTimeLimitStrategy": "JAPANESE_SETTINGS",
  "cardPreprocessingStrategy": "NONE",
  "discordFinalAnswerListElementStrategy": "QUESTION_AND_ANSWER_LINK_QUESTION",
  "scoreAnswerStrategy": "ONE_ANSWER_ONE_POINT",
  "additionalAnswerWaitStrategy": "JAPANESE_SETTINGS",
  "discordIntermediateAnswerListElementStrategy": "CORRECT_ANSWERS",
  "answerCompareStrategy": "CONVERT_KANA",
  "commentFieldName": "Line(s)",
  "description": "[Kagoshima station names](https://mb.jorudan.co.jp/os/eki/menu_koj/)",
  "cards": [
    {
      "question": "姶良",
      "answer": [
        "あいら"
      ],
      "meaning": "日豊本線",
      "dictionaryLinkUri": "https://mb.jorudan.co.jp/os/eki/aira/"
    },
    {
      "question": "阿久根",
      "answer": [
        "あくね"
      ],
      "meaning": "肥薩おれんじ鉄道",
      "dictionaryLinkUri": "https://mb.jorudan.co.jp/os/eki/akune/"
    },
    {
      "question": "朝日通",
      "answer": [
        "あさひどおり"
      ],
      "meaning": "鹿児島市電１系統など",
      "dictionaryLinkUri": "https://mb.jorudan.co.jp/os/eki/asahidori/"
    },
    {
      "question": "荒田八幡",
      "answer": [
        "あらたはちまん"
      ],
      "meaning": "鹿児島市電１系統",
      "dictionaryLinkUri": "https://mb.jorudan.co.jp/os/eki/aratahachiman/"
    },
    {
      "question": "石垣",
      "answer": [
        "いしかき"
      ],
      "meaning": "指宿枕崎線",
      "dictionaryLinkUri": "https://mb.jorudan.co.jp/os/eki/ishikaki/"
    },
    {
      "question": "伊集院",
      "answer": [
        "いじゅういん"
      ],
      "meaning": "鹿児島本線",
      "dictionaryLinkUri": "https://mb.jorudan.co.jp/os/eki/ijuin/"
    },
    {
      "question": "出水",
      "answer": [
        "いずみ"
      ],
      "meaning": "九州新幹線、肥薩おれんじ鉄道",
      "dictionaryLinkUri": "https://mb.jorudan.co.jp/os/eki/izumi_kagoshima/"
    },
    {
      "question": "市来",
      "answer": [
        "いちき"
      ],
      "meaning": "鹿児島本線",
      "dictionaryLinkUri": "https://mb.jorudan.co.jp/os/eki/ichiki/"
    },
    {
      "question": "いづろ通",
      "answer": [
        "いづろどおり"
      ],
      "meaning": "鹿児島市電１系統など",
      "dictionaryLinkUri": "https://mb.jorudan.co.jp/os/eki/izurodori/"
    },
    {
      "question": "指宿",
      "answer": [
        "いぶすき"
      ],
      "meaning": "指宿枕崎線",
      "dictionaryLinkUri": "https://mb.jorudan.co.jp/os/eki/ibusuki/"
    },
    {
      "question": "入野",
      "answer": [
        "いりの"
      ],
      "meaning": "指宿枕崎線",
      "dictionaryLinkUri": "https://mb.jorudan.co.jp/os/eki/irino_kagoshima/"
    },
    {
      "question": "植村",
      "answer": [
        "うえむら"
      ],
      "meaning": "肥薩線",
      "dictionaryLinkUri": "https://mb.jorudan.co.jp/os/eki/uemura/"
    },
    {
      "question": "牛ノ浜",
      "answer": [
        "うしのはま"
      ],
      "meaning": "肥薩おれんじ鉄道",
      "dictionaryLinkUri": "https://mb.jorudan.co.jp/os/eki/ushinohama/"
    },
    {
      "question": "宇宿",
      "answer": [
        "うすき"
      ],
      "meaning": "指宿枕崎線",
      "dictionaryLinkUri": "https://mb.jorudan.co.jp/os/eki/usuki_kagoshima/"
    },
    {
      "question": "宇宿一丁目",
      "answer": [
        "うすきいっちょうめ"
      ],
      "meaning": "鹿児島市電１系統",
      "dictionaryLinkUri": "https://mb.jorudan.co.jp/os/eki/usukiicchome/"
    },
    {
      "question": "頴娃",
      "answer": [
        "えい"
      ],
      "meaning": "指宿枕崎線",
      "dictionaryLinkUri": "https://mb.jorudan.co.jp/os/eki/ei/"
    },
    {
      "question": "頴娃大川",
      "answer": [
        "えいおおかわ"
      ],
      "meaning": "指宿枕崎線",
      "dictionaryLinkUri": "https://mb.jorudan.co.jp/os/eki/ei-okawa/"
    },
    {
      "question": "大隅大川原",
      "answer": [
        "おおすみおおかわら"
      ],
      "meaning": "日豊本線",
      "dictionaryLinkUri": "https://mb.jorudan.co.jp/os/eki/osumi-okawara/"
    },
    {
      "question": "大隅夏井",
      "answer": [
        "おおすみなつい"
      ],
      "meaning": "日南線",
      "dictionaryLinkUri": "https://mb.jorudan.co.jp/os/eki/osumi-natsui/"
    },
    {
      "question": "大隅横川",
      "answer": [
        "おおすみよこがわ"
      ],
      "meaning": "肥薩線",
      "dictionaryLinkUri": "https://mb.jorudan.co.jp/os/eki/osumi-yokogawa/"
    },
    {
      "question": "大山",
      "answer": [
        "おおやま"
      ],
      "meaning": "指宿枕崎線",
      "dictionaryLinkUri": "https://mb.jorudan.co.jp/os/eki/oyama_kagoshima/"
    },
    {
      "question": "折口",
      "answer": [
        "おりぐち"
      ],
      "meaning": "肥薩おれんじ鉄道",
      "dictionaryLinkUri": "https://mb.jorudan.co.jp/os/eki/origuchi/"
    },
    {
      "question": "開聞",
      "answer": [
        "かいもん"
      ],
      "meaning": "指宿枕崎線",
      "dictionaryLinkUri": "https://mb.jorudan.co.jp/os/eki/kaimon/"
    },
    {
      "question": "鹿児島",
      "answer": [
        "かごしま"
      ],
      "meaning": "鹿児島本線、日豊本線",
      "dictionaryLinkUri": "https://mb.jorudan.co.jp/os/eki/kagoshima/"
    },
    {
      "question": "鹿児島駅前",
      "answer": [
        "かごしまえきまえ"
      ],
      "meaning": "鹿児島市電１系統など",
      "dictionaryLinkUri": "https://mb.jorudan.co.jp/os/eki/kagoshimaekimae/"
    },
    {
      "question": "鹿児島中央",
      "answer": [
        "かごしまちゅうおう"
      ],
      "meaning": "鹿児島本線、日豊本線など",
      "dictionaryLinkUri": "https://mb.jorudan.co.jp/os/eki/kagoshimachuo/"
    },
    {
      "question": "鹿児島中央駅前",
      "answer": [
        "かごしまちゅうおうえきまえ"
      ],
      "meaning": "鹿児島市電２系統",
      "dictionaryLinkUri": "https://mb.jorudan.co.jp/os/eki/kagoshimachuoekimae/"
    },
    {
      "question": "加治木",
      "answer": [
        "かじき"
      ],
      "meaning": "日豊本線",
      "dictionaryLinkUri": "https://mb.jorudan.co.jp/os/eki/kajiki/"
    },
    {
      "question": "加治屋町",
      "answer": [
        "かじやまち"
      ],
      "meaning": "鹿児島市電２系統",
      "dictionaryLinkUri": "https://mb.jorudan.co.jp/os/eki/kajiyamachi/"
    },
    {
      "question": "上伊集院",
      "answer": [
        "かみいじゅういん"
      ],
      "meaning": "鹿児島本線",
      "dictionaryLinkUri": "https://mb.jorudan.co.jp/os/eki/kami-ijuin/"
    },
    {
      "question": "上塩屋",
      "answer": [
        "かみしおや"
      ],
      "meaning": "鹿児島市電１系統",
      "dictionaryLinkUri": "https://mb.jorudan.co.jp/os/eki/kamishioya/"
    },
    {
      "question": "上川内",
      "answer": [
        "かみせんだい"
      ],
      "meaning": "肥薩おれんじ鉄道",
      "dictionaryLinkUri": "https://mb.jorudan.co.jp/os/eki/kami-sendai/"
    },
    {
      "question": "神村学園前",
      "answer": [
        "かみむらがくえんまえ"
      ],
      "meaning": "鹿児島本線",
      "dictionaryLinkUri": "https://mb.jorudan.co.jp/os/eki/kamimuragakuen-mae/"
    },
    {
      "question": "鴨池",
      "answer": [
        "かもいけ"
      ],
      "meaning": "鹿児島市電１系統",
      "dictionaryLinkUri": "https://mb.jorudan.co.jp/os/eki/kamoike/"
    },
    {
      "question": "嘉例川",
      "answer": [
        "かれいがわ"
      ],
      "meaning": "肥薩線",
      "dictionaryLinkUri": "https://mb.jorudan.co.jp/os/eki/kareigawa/"
    },
    {
      "question": "喜入",
      "answer": [
        "きいれ"
      ],
      "meaning": "指宿枕崎線",
      "dictionaryLinkUri": "https://mb.jorudan.co.jp/os/eki/kiire/"
    },
    {
      "question": "騎射場",
      "answer": [
        "きしゃば"
      ],
      "meaning": "鹿児島市電１系統",
      "dictionaryLinkUri": "https://mb.jorudan.co.jp/os/eki/kishaba/"
    },
    {
      "question": "北永野田",
      "answer": [
        "きたながのだ"
      ],
      "meaning": "日豊本線",
      "dictionaryLinkUri": "https://mb.jorudan.co.jp/os/eki/kita-naganoda/"
    },
    {
      "question": "北俣",
      "answer": [
        "きたまた"
      ],
      "meaning": "日豊本線",
      "dictionaryLinkUri": "https://mb.jorudan.co.jp/os/eki/kitamata/"
    },
    {
      "question": "霧島温泉",
      "answer": [
        "きりしまおんせん"
      ],
      "meaning": "肥薩線",
      "dictionaryLinkUri": "https://mb.jorudan.co.jp/os/eki/kirishima-onsen/"
    },
    {
      "question": "霧島神宮",
      "answer": [
        "きりしまじんぐう"
      ],
      "meaning": "日豊本線",
      "dictionaryLinkUri": "https://mb.jorudan.co.jp/os/eki/kirishima-jingu/"
    },
    {
      "question": "錦江",
      "answer": [
        "きんこう"
      ],
      "meaning": "日豊本線",
      "dictionaryLinkUri": "https://mb.jorudan.co.jp/os/eki/kinko/"
    },
    {
      "question": "草道",
      "answer": [
        "くさみち"
      ],
      "meaning": "肥薩おれんじ鉄道",
      "dictionaryLinkUri": "https://mb.jorudan.co.jp/os/eki/kusamichi/"
    },
    {
      "question": "串木野",
      "answer": [
        "くしきの"
      ],
      "meaning": "鹿児島本線",
      "dictionaryLinkUri": "https://mb.jorudan.co.jp/os/eki/kushikino/"
    },
    {
      "question": "隈之城",
      "answer": [
        "くまのじょう"
      ],
      "meaning": "鹿児島本線",
      "dictionaryLinkUri": "https://mb.jorudan.co.jp/os/eki/kumanojo/"
    },
    {
      "question": "栗野",
      "answer": [
        "くりの"
      ],
      "meaning": "肥薩線",
      "dictionaryLinkUri": "https://mb.jorudan.co.jp/os/eki/kurino/"
    },
    {
      "question": "工学部前",
      "answer": [
        "こうがくぶまえ"
      ],
      "meaning": "鹿児島市電２系統",
      "dictionaryLinkUri": "https://mb.jorudan.co.jp/os/eki/kogakubu-mae/"
    },
    {
      "question": "甲東中学校前",
      "answer": [
        "こうとうちゅうがっこうまえ"
      ],
      "meaning": "鹿児島市電１系統",
      "dictionaryLinkUri": "https://mb.jorudan.co.jp/os/eki/kotochugakko-mae/"
    },
    {
      "question": "郡元",
      "answer": [
        "こおりもと"
      ],
      "meaning": "鹿児島市電１系統など",
      "dictionaryLinkUri": "https://mb.jorudan.co.jp/os/eki/korimoto_kagoshima-shiden/"
    },
    {
      "question": "国分",
      "answer": [
        "こくぶ"
      ],
      "meaning": "日豊本線",
      "dictionaryLinkUri": "https://mb.jorudan.co.jp/os/eki/kokubu_kagoshima/"
    },
    {
      "question": "木場茶屋",
      "answer": [
        "こばんちゃや"
      ],
      "meaning": "鹿児島本線",
      "dictionaryLinkUri": "https://mb.jorudan.co.jp/os/eki/kobanchaya/"
    },
    {
      "question": "米ノ津",
      "answer": [
        "こめのつ"
      ],
      "meaning": "肥薩おれんじ鉄道",
      "dictionaryLinkUri": "https://mb.jorudan.co.jp/os/eki/komenotsu/"
    },
    {
      "question": "五位野",
      "answer": [
        "ごいの"
      ],
      "meaning": "指宿枕崎線",
      "dictionaryLinkUri": "https://mb.jorudan.co.jp/os/eki/goino/"
    },
    {
      "question": "御領",
      "answer": [
        "ごりょう"
      ],
      "meaning": "指宿枕崎線",
      "dictionaryLinkUri": "https://mb.jorudan.co.jp/os/eki/goryo_kagoshima/"
    },
    {
      "question": "坂之上",
      "answer": [
        "さかのうえ"
      ],
      "meaning": "指宿枕崎線",
      "dictionaryLinkUri": "https://mb.jorudan.co.jp/os/eki/sakano-ue/"
    },
    {
      "question": "桜島桟橋通",
      "answer": [
        "さくらじまさんばしどおり"
      ],
      "meaning": "鹿児島市電１系統など",
      "dictionaryLinkUri": "https://mb.jorudan.co.jp/os/eki/sakurajima_sambashi-dori/"
    },
    {
      "question": "笹貫",
      "answer": [
        "ささぬき"
      ],
      "meaning": "鹿児島市電１系統",
      "dictionaryLinkUri": "https://mb.jorudan.co.jp/os/eki/sasanuki/"
    },
    {
      "question": "薩摩板敷",
      "answer": [
        "さつまいたしき"
      ],
      "meaning": "指宿枕崎線",
      "dictionaryLinkUri": "https://mb.jorudan.co.jp/os/eki/satsuma-itashiki/"
    },
    {
      "question": "薩摩今和泉",
      "answer": [
        "さつまいまいずみ"
      ],
      "meaning": "指宿枕崎線",
      "dictionaryLinkUri": "https://mb.jorudan.co.jp/os/eki/satsuma-imaizumi/"
    },
    {
      "question": "薩摩大川",
      "answer": [
        "さつまおおかわ"
      ],
      "meaning": "肥薩おれんじ鉄道",
      "dictionaryLinkUri": "https://mb.jorudan.co.jp/os/eki/satsuma-okawa/"
    },
    {
      "question": "薩摩川尻",
      "answer": [
        "さつまかわしり"
      ],
      "meaning": "指宿枕崎線",
      "dictionaryLinkUri": "https://mb.jorudan.co.jp/os/eki/satsuma-kawashiri/"
    },
    {
      "question": "薩摩塩屋",
      "answer": [
        "さつましおや"
      ],
      "meaning": "指宿枕崎線",
      "dictionaryLinkUri": "https://mb.jorudan.co.jp/os/eki/satsuma-shioya/"
    },
    {
      "question": "薩摩高城",
      "answer": [
        "さつまたき"
      ],
      "meaning": "肥薩おれんじ鉄道",
      "dictionaryLinkUri": "https://mb.jorudan.co.jp/os/eki/satsuma-taki/"
    },
    {
      "question": "薩摩松元",
      "answer": [
        "さつままつもと"
      ],
      "meaning": "鹿児島本線",
      "dictionaryLinkUri": "https://mb.jorudan.co.jp/os/eki/satsuma-matsumoto/"
    },
    {
      "question": "重富",
      "answer": [
        "しげとみ"
      ],
      "meaning": "日豊本線",
      "dictionaryLinkUri": "https://mb.jorudan.co.jp/os/eki/shigetomi/"
    },
    {
      "question": "志布志",
      "answer": [
        "しぶし"
      ],
      "meaning": "日南線",
      "dictionaryLinkUri": "https://mb.jorudan.co.jp/os/eki/shibushi/"
    },
    {
      "question": "市役所前",
      "answer": [
        "しやくしょまえ"
      ],
      "meaning": "鹿児島市電１系統など",
      "dictionaryLinkUri": "https://mb.jorudan.co.jp/os/eki/shiyakusho-mae_kagoshima/"
    },
    {
      "question": "白沢",
      "answer": [
        "しらさわ"
      ],
      "meaning": "指宿枕崎線",
      "dictionaryLinkUri": "https://mb.jorudan.co.jp/os/eki/shirasawa_kagoshima/"
    },
    {
      "question": "市立病院前",
      "answer": [
        "しりつびょういんまえ"
      ],
      "meaning": "鹿児島市電２系統",
      "dictionaryLinkUri": "https://mb.jorudan.co.jp/os/eki/shiritsu-byoin-mae_kagoshimashi/"
    },
    {
      "question": "神田",
      "answer": [
        "しんでん"
      ],
      "meaning": "鹿児島市電２系統",
      "dictionaryLinkUri": "https://mb.jorudan.co.jp/os/eki/shinden_kagoshima/"
    },
    {
      "question": "新屋敷",
      "answer": [
        "しんやしき"
      ],
      "meaning": "鹿児島市電１系統",
      "dictionaryLinkUri": "https://mb.jorudan.co.jp/os/eki/shin-yashiki/"
    },
    {
      "question": "慈眼寺",
      "answer": [
        "じげんじ"
      ],
      "meaning": "指宿枕崎線",
      "dictionaryLinkUri": "https://mb.jorudan.co.jp/os/eki/jigenji/"
    },
    {
      "question": "純心学園前",
      "answer": [
        "じゅんしんがくえんまえ"
      ],
      "meaning": "鹿児島市電２系統",
      "dictionaryLinkUri": "https://mb.jorudan.co.jp/os/eki/junshingakuen-mae/"
    },
    {
      "question": "水族館口",
      "answer": [
        "すいぞくかんぐち"
      ],
      "meaning": "鹿児島市電１系統など",
      "dictionaryLinkUri": "https://mb.jorudan.co.jp/os/eki/suizokukanguchi/"
    },
    {
      "question": "瀬々串",
      "answer": [
        "せせくし"
      ],
      "meaning": "指宿枕崎線",
      "dictionaryLinkUri": "https://mb.jorudan.co.jp/os/eki/sesekushi/"
    },
    {
      "question": "川内",
      "answer": [
        "せんだい"
      ],
      "meaning": "JR線、肥薩おれんじ鉄道",
      "dictionaryLinkUri": "https://mb.jorudan.co.jp/os/eki/sendai_kagoshima/"
    },
    {
      "question": "高尾野",
      "answer": [
        "たかおの"
      ],
      "meaning": "肥薩おれんじ鉄道",
      "dictionaryLinkUri": "https://mb.jorudan.co.jp/os/eki/takaono/"
    },
    {
      "question": "高見橋",
      "answer": [
        "たかみばし"
      ],
      "meaning": "鹿児島市電２系統",
      "dictionaryLinkUri": "https://mb.jorudan.co.jp/os/eki/takamibashi/"
    },
    {
      "question": "高見馬場",
      "answer": [
        "たかみばば"
      ],
      "meaning": "鹿児島市電１系統など",
      "dictionaryLinkUri": "https://mb.jorudan.co.jp/os/eki/takamibaba/"
    },
    {
      "question": "財部",
      "answer": [
        "たからべ"
      ],
      "meaning": "日豊本線",
      "dictionaryLinkUri": "https://mb.jorudan.co.jp/os/eki/takarabe/"
    },
    {
      "question": "武之橋",
      "answer": [
        "たけのはし"
      ],
      "meaning": "鹿児島市電１系統",
      "dictionaryLinkUri": "https://mb.jorudan.co.jp/os/eki/takenohashi/"
    },
    {
      "question": "谷山",
      "answer": [
        "たにやま"
      ],
      "meaning": "鹿児島市電１系統",
      "dictionaryLinkUri": "https://mb.jorudan.co.jp/os/eki/taniyama_kagoshima-shiden/"
    },
    {
      "question": "帖佐",
      "answer": [
        "ちょうさ"
      ],
      "meaning": "日豊本線",
      "dictionaryLinkUri": "https://mb.jorudan.co.jp/os/eki/chosa/"
    },
    {
      "question": "鶴丸",
      "answer": [
        "つるまる"
      ],
      "meaning": "吉都線",
      "dictionaryLinkUri": "https://mb.jorudan.co.jp/os/eki/tsurumaru/"
    },
    {
      "question": "天文館通",
      "answer": [
        "てんもんかんどおり"
      ],
      "meaning": "鹿児島市電１系統など",
      "dictionaryLinkUri": "https://mb.jorudan.co.jp/os/eki/temmonkandori/"
    },
    {
      "question": "唐湊",
      "answer": [
        "とそ"
      ],
      "meaning": "鹿児島市電２系統",
      "dictionaryLinkUri": "https://mb.jorudan.co.jp/os/eki/toso/"
    },
    {
      "question": "中郡",
      "answer": [
        "なかごおり"
      ],
      "meaning": "鹿児島市電２系統",
      "dictionaryLinkUri": "https://mb.jorudan.co.jp/os/eki/nakagori_kagoshima/"
    },
    {
      "question": "中洲通",
      "answer": [
        "なかすどおり"
      ],
      "meaning": "鹿児島市電２系統",
      "dictionaryLinkUri": "https://mb.jorudan.co.jp/os/eki/nakasudori/"
    },
    {
      "question": "中福良",
      "answer": [
        "なかふくら"
      ],
      "meaning": "肥薩線",
      "dictionaryLinkUri": "https://mb.jorudan.co.jp/os/eki/naka-fukura/"
    },
    {
      "question": "中名",
      "answer": [
        "なかみょう"
      ],
      "meaning": "指宿枕崎線",
      "dictionaryLinkUri": "https://mb.jorudan.co.jp/os/eki/nakamyo/"
    },
    {
      "question": "涙橋",
      "answer": [
        "なみだばし"
      ],
      "meaning": "鹿児島市電１系統",
      "dictionaryLinkUri": "https://mb.jorudan.co.jp/os/eki/namidabashi/"
    },
    {
      "question": "二月田",
      "answer": [
        "にがつでん"
      ],
      "meaning": "指宿枕崎線",
      "dictionaryLinkUri": "https://mb.jorudan.co.jp/os/eki/nigatsuden/"
    },
    {
      "question": "二軒茶屋",
      "answer": [
        "にけんぢゃや"
      ],
      "meaning": "鹿児島市電１系統",
      "dictionaryLinkUri": "https://mb.jorudan.co.jp/os/eki/nikenjaya_kagoshima/"
    },
    {
      "question": "西出水",
      "answer": [
        "にしいずみ"
      ],
      "meaning": "肥薩おれんじ鉄道",
      "dictionaryLinkUri": "https://mb.jorudan.co.jp/os/eki/nishi-izumi_kagoshima/"
    },
    {
      "question": "西頴娃",
      "answer": [
        "にしえい"
      ],
      "meaning": "指宿枕崎線",
      "dictionaryLinkUri": "https://mb.jorudan.co.jp/os/eki/nishi-ei/"
    },
    {
      "question": "西大山",
      "answer": [
        "にしおおやま"
      ],
      "meaning": "指宿枕崎線",
      "dictionaryLinkUri": "https://mb.jorudan.co.jp/os/eki/nishi-oyama/"
    },
    {
      "question": "西方",
      "answer": [
        "にしかた"
      ],
      "meaning": "肥薩おれんじ鉄道",
      "dictionaryLinkUri": "https://mb.jorudan.co.jp/os/eki/nishikata/"
    },
    {
      "question": "二中通",
      "answer": [
        "にちゅうどおり"
      ],
      "meaning": "鹿児島市電１系統",
      "dictionaryLinkUri": "https://mb.jorudan.co.jp/os/eki/nichudori/"
    },
    {
      "question": "生見",
      "answer": [
        "ぬくみ"
      ],
      "meaning": "指宿枕崎線",
      "dictionaryLinkUri": "https://mb.jorudan.co.jp/os/eki/nukumi/"
    },
    {
      "question": "野田郷",
      "answer": [
        "のだごう"
      ],
      "meaning": "肥薩おれんじ鉄道",
      "dictionaryLinkUri": "https://mb.jorudan.co.jp/os/eki/nodago/"
    },
    {
      "question": "隼人",
      "answer": [
        "はやと"
      ],
      "meaning": "日豊本線、肥薩線",
      "dictionaryLinkUri": "https://mb.jorudan.co.jp/os/eki/hayato_kagoshima/"
    },
    {
      "question": "東市来",
      "answer": [
        "ひがしいちき"
      ],
      "meaning": "鹿児島本線",
      "dictionaryLinkUri": "https://mb.jorudan.co.jp/os/eki/higashi-ichiki/"
    },
    {
      "question": "東開聞",
      "answer": [
        "ひがしかいもん"
      ],
      "meaning": "指宿枕崎線",
      "dictionaryLinkUri": "https://mb.jorudan.co.jp/os/eki/higashi-kaimon/"
    },
    {
      "question": "日当山",
      "answer": [
        "ひなたやま"
      ],
      "meaning": "肥薩線",
      "dictionaryLinkUri": "https://mb.jorudan.co.jp/os/eki/hinatayama/"
    },
    {
      "question": "表木山",
      "answer": [
        "ひょうきやま"
      ],
      "meaning": "肥薩線",
      "dictionaryLinkUri": "https://mb.jorudan.co.jp/os/eki/hyokiyama/"
    },
    {
      "question": "平川",
      "answer": [
        "ひらかわ"
      ],
      "meaning": "指宿枕崎線",
      "dictionaryLinkUri": "https://mb.jorudan.co.jp/os/eki/hirakawa/"
    },
    {
      "question": "広木",
      "answer": [
        "ひろき"
      ],
      "meaning": "鹿児島本線",
      "dictionaryLinkUri": "https://mb.jorudan.co.jp/os/eki/hiroki/"
    },
    {
      "question": "前之浜",
      "answer": [
        "まえのはま"
      ],
      "meaning": "指宿枕崎線",
      "dictionaryLinkUri": "https://mb.jorudan.co.jp/os/eki/maenohama/"
    },
    {
      "question": "枕崎",
      "answer": [
        "まくらざき"
      ],
      "meaning": "指宿枕崎線",
      "dictionaryLinkUri": "https://mb.jorudan.co.jp/os/eki/makurazaki/"
    },
    {
      "question": "松ヶ浦",
      "answer": [
        "まつがうら"
      ],
      "meaning": "指宿枕崎線",
      "dictionaryLinkUri": "https://mb.jorudan.co.jp/os/eki/matsugaura/"
    },
    {
      "question": "水成川",
      "answer": [
        "みずなりかわ"
      ],
      "meaning": "指宿枕崎線",
      "dictionaryLinkUri": "https://mb.jorudan.co.jp/os/eki/mizunarikawa/"
    },
    {
      "question": "南鹿児島",
      "answer": [
        "みなみかごしま"
      ],
      "meaning": "指宿枕崎線",
      "dictionaryLinkUri": "https://mb.jorudan.co.jp/os/eki/minami-kagoshima/"
    },
    {
      "question": "南鹿児島駅前",
      "answer": [
        "みなみかごしまえきまえ"
      ],
      "meaning": "鹿児島市電１系統",
      "dictionaryLinkUri": "https://mb.jorudan.co.jp/os/eki/minamikagoshimaekimae/"
    },
    {
      "question": "宮ヶ浜",
      "answer": [
        "みやがはま"
      ],
      "meaning": "指宿枕崎線",
      "dictionaryLinkUri": "https://mb.jorudan.co.jp/os/eki/miyagahama/"
    },
    {
      "question": "都通",
      "answer": [
        "みやこどおり"
      ],
      "meaning": "鹿児島市電２系統",
      "dictionaryLinkUri": "https://mb.jorudan.co.jp/os/eki/miyakodori/"
    },
    {
      "question": "山川",
      "answer": [
        "やまかわ"
      ],
      "meaning": "指宿枕崎線",
      "dictionaryLinkUri": "https://mb.jorudan.co.jp/os/eki/yamakawa/"
    },
    {
      "question": "湯之元",
      "answer": [
        "ゆのもと"
      ],
      "meaning": "鹿児島本線",
      "dictionaryLinkUri": "https://mb.jorudan.co.jp/os/eki/yunomoto/"
    },
    {
      "question": "吉松",
      "answer": [
        "よしまつ"
      ],
      "meaning": "肥薩線、吉都線",
      "dictionaryLinkUri": "https://mb.jorudan.co.jp/os/eki/yoshimatsu/"
    },
    {
      "question": "竜ヶ水",
      "answer": [
        "りゅうがみず"
      ],
      "meaning": "日豊本線",
      "dictionaryLinkUri": "https://mb.jorudan.co.jp/os/eki/ryugamizu/"
    },
    {
      "question": "脇田",
      "answer": [
        "わきだ"
      ],
      "meaning": "鹿児島市電１系統",
      "dictionaryLinkUri": "https://mb.jorudan.co.jp/os/eki/wakida/"
    }
  ]
}